biosignalsnotebooks/__init__.py
biosignalsnotebooks/__notebook_support__.py
biosignalsnotebooks/android.py
biosignalsnotebooks/aux_functions.py
biosignalsnotebooks/conversion.py
biosignalsnotebooks/detect.py
biosignalsnotebooks/extract.py
biosignalsnotebooks/factory.py
biosignalsnotebooks/load.py
biosignalsnotebooks/process.py
biosignalsnotebooks/signal_samples.py
biosignalsnotebooks/synchronisation.py
biosignalsnotebooks/train_and_classify.py
biosignalsnotebooks/visualise.py
biosignalsnotebooks/external_packages/novainstrumentation/ARparameters.py
biosignalsnotebooks/external_packages/novainstrumentation/__init__.py
biosignalsnotebooks/external_packages/novainstrumentation/figtools.py
biosignalsnotebooks/external_packages/novainstrumentation/filter.py
biosignalsnotebooks/external_packages/novainstrumentation/freq_analysis.py
biosignalsnotebooks/external_packages/novainstrumentation/niplot.py
biosignalsnotebooks/external_packages/novainstrumentation/peakdelta.py
biosignalsnotebooks/external_packages/novainstrumentation/peaks.py
biosignalsnotebooks/external_packages/novainstrumentation/smooth.py
biosignalsnotebooks/external_packages/novainstrumentation/stat_analysis.py
biosignalsnotebooks/external_packages/novainstrumentation/tictac.py
biosignalsnotebooks/external_packages/novainstrumentation/tools.py
biosignalsnotebooks/external_packages/novainstrumentation/__pycache__/__init__.cpython-36.pyc
biosignalsnotebooks/external_packages/novainstrumentation/__pycache__/figtools.cpython-36.pyc
biosignalsnotebooks/external_packages/novainstrumentation/__pycache__/filter.cpython-36.pyc
biosignalsnotebooks/external_packages/novainstrumentation/__pycache__/freq_analysis.cpython-36.pyc
biosignalsnotebooks/external_packages/novainstrumentation/__pycache__/niplot.cpython-36.pyc
biosignalsnotebooks/external_packages/novainstrumentation/__pycache__/peakdelta.cpython-36.pyc
biosignalsnotebooks/external_packages/novainstrumentation/__pycache__/peaks.cpython-36.pyc
biosignalsnotebooks-0.6.14.dist-info/LICENSE.txt
biosignalsnotebooks-0.6.14.dist-info/METADATA
biosignalsnotebooks-0.6.14.dist-info/WHEEL
biosignalsnotebooks-0.6.14.dist-info/top_level.txt
biosignalsnotebooks-0.6.14.dist-info/RECORD
