Metadata-Version: 2.1
Name: biosignalsnotebooks
Version: 0.6.14
Summary: A Python package for supporting the external loading and processing of OpenSignals electrophysiological acquisitions.
Home-page: https://github.com/biosignalsplux/biosignalsnotebooks
Author: PLUX Wireless Biosignals
Author-email: gramos@plux.info
License: MIT
Platform: win32
Platform: darwin
Platform: os2
Platform: os2emx
License-File: LICENSE.txt
Requires-Dist: numpy (==1.22.2)
Requires-Dist: matplotlib
Requires-Dist: scipy (==1.8.1)
Requires-Dist: h5py
Requires-Dist: wget
Requires-Dist: datetime
Requires-Dist: bokeh (==2.4.3)
Requires-Dist: scipy
Requires-Dist: IPython
Requires-Dist: pandas
Requires-Dist: nbformat
Requires-Dist: ipython
Requires-Dist: requests
Requires-Dist: libmagic
Requires-Dist: python-magic-bin ; platform_system != "Linux"
Requires-Dist: python-magic ; platform_system == "Linux"
